lexrchainer_client/__init__.py
lexrchainer_client/agent_builder.py
lexrchainer_client/client_interface.py
lexrchainer_client/config.py
lexrchainer_client/models.py
lexrchainer_client-0.1.6.dist-info/METADATA
lexrchainer_client-0.1.6.dist-info/WHEEL
lexrchainer_client-0.1.6.dist-info/RECORD
