Metadata-Version: 2.4
Name: lexrchainer-client
Version: 0.1.6
Summary: Python client library for interacting with the LexrChainer API
Project-URL: Homepage, https://github.com/yourusername/lexrchainer
Project-URL: Documentation, https://lexrchainer.readthedocs.io/
Project-URL: Repository, https://github.com/yourusername/lexrchainer.git
Project-URL: Issues, https://github.com/yourusername/lexrchainer/issues
Author: LexrChainer Team
License-Expression: MIT
Keywords: agent,ai,api,conversation,llm
Classifier: Development Status :: 4 - Beta
Classifier: Intended Audience :: Developers
Classifier: License :: OSI Approved :: MIT License
Classifier: Programming Language :: Python :: 3
Classifier: Programming Language :: Python :: 3.8
Classifier: Programming Language :: Python :: 3.9
Classifier: Programming Language :: Python :: 3.10
Classifier: Programming Language :: Python :: 3.11
Classifier: Topic :: Software Development :: Libraries :: Python Modules
Requires-Python: >=3.8
Requires-Dist: pydantic>=2.0.0
Requires-Dist: python-dotenv>=1.0.0
Requires-Dist: requests>=2.31.0
Provides-Extra: dev
Requires-Dist: black>=23.0.0; extra == 'dev'
Requires-Dist: isort>=5.0.0; extra == 'dev'
Requires-Dist: mypy>=1.0.0; extra == 'dev'
Requires-Dist: pytest-cov>=4.0.0; extra == 'dev'
Requires-Dist: pytest>=7.0.0; extra == 'dev'
Requires-Dist: ruff>=0.1.0; extra == 'dev'
